CloudWatch_Agent_Installer/__init__.py
CloudWatch_Agent_Installer/config.py
CloudWatch_Agent_Installer/installer.py
CloudWatch_Agent_Installer/main.py
test/__init__.py
test/test_installer.py
test/test_ssh_connection.py
test/test_winrm_connection.py
cloudwatch_agent_installer-0.2.4.dist-info/LICENSE
cloudwatch_agent_installer-0.2.4.dist-info/METADATA
cloudwatch_agent_installer-0.2.4.dist-info/WHEEL
cloudwatch_agent_installer-0.2.4.dist-info/entry_points.txt
cloudwatch_agent_installer-0.2.4.dist-info/top_level.txt
cloudwatch_agent_installer-0.2.4.dist-info/RECORD
