Metadata-Version: 2.1
Name: cloudwatch_agent_installer
Version: 0.2.4
Summary: Programa de instalacion de CloudWatch Agent para instancias de EC2 con linux y windows
Home-page: https://github.com/JoseDavidN/CloudWatch_Agent_Installer
Author: Jose David Gomez
Author-email: gomezjosedavid997@gmail.com
Classifier: Programming Language :: Python :: 3
Classifier: License :: OSI Approved :: MIT License
Classifier: Operating System :: OS Independent
Requires-Python: >=3.6
License-File: LICENSE
Requires-Dist: boto3
Requires-Dist: paramiko
Requires-Dist: pywinrm
